{
    "version": "5.2",
    "groups": [
        {
            "id": 1,
            "title": "Perso",
            "iconColor": "#e69138",
            "iconUrl": null,
            "iconViewType": "squares",
            "tabs": [
                {
                    "url": "https://mail.proton.me/u/100/inbox",
                    "title": "Boite de réception | roullois.leo@protonmail.com | Proton Mail",
                    "cookieStoreId": "firefox-container-1",
                    "id": 3
                },
                {
                    "url": "https://mail.google.com/mail/u/1/#inbox",
                    "title": "Messagerie ESIEE",
                    "cookieStoreId": "firefox-container-1",
                    "id": 2
                }
            ],
            "isArchive": false,
            "newTabContainer": "firefox-container-1",
            "ifDifferentContainerReOpen": false,
            "excludeContainersForReOpen": [
                "firefox-default"
            ],
            "isSticky": false,
            "catchTabContainers": [],
            "catchTabRules": "",
            "muteTabsWhenGroupCloseAndRestoreWhenOpen": false,
            "showTabAfterMovingItIntoThisGroup": false,
            "bookmarkId": null,
            "showOnlyActiveTabAfterMovingItIntoThisGroup": false,
            "discardTabsAfterHide": false,
            "discardExcludeAudioTabs": false,
            "prependTitleToWindow": false,
            "exportToBookmarksWhenAutoBackup": true,
            "leaveBookmarksOfClosedTabs": false,
            "moveToGroupIfNoneCatchTabRules": null
        },
        {
            "id": 3,
            "title": "Infosec",
            "iconColor": "#674ea7",
            "iconUrl": null,
            "iconViewType": "squares",
            "tabs": [
                {
                    "url": "https://www.root-me.org/ley0x?lang=fr#54fab022fe9899e47aa0b3d40ecc27f2",
                    "title": "profil de ley0x [Root Me : plateforme d'apprentissage dédiée au Hacking et à la Sécurité de l'Information]",
                    "cookieStoreId": "firefox-container-6",
                    "id": 7
                },
                {
                    "url": "https://www.root-me.org/fr/Challenges/Programmation/TCP-Retour-au-college?lang=fr",
                    "title": "Challenges/Programmation : TCP - Retour au collège [Root Me : plateforme d'apprentissage dédiée au Hacking et à la Sécurité de l'Information]",
                    "cookieStoreId": "firefox-container-6",
                    "id": 8
                },
                {
                    "url": "https://tryhackme.com/dashboard",
                    "title": "TryHackMe | Dashboard",
                    "cookieStoreId": "firefox-container-6",
                    "id": 10
                },
                {
                    "url": "https://github.com/leoroullois/dotfiles",
                    "title": "leoroullois/dotfiles",
                    "cookieStoreId": "firefox-container-6",
                    "id": 11
                }
            ],
            "isArchive": false,
            "newTabContainer": "firefox-container-6",
            "ifDifferentContainerReOpen": false,
            "excludeContainersForReOpen": [],
            "isSticky": false,
            "catchTabContainers": [
                "firefox-container-6"
            ],
            "catchTabRules": "",
            "muteTabsWhenGroupCloseAndRestoreWhenOpen": false,
            "showTabAfterMovingItIntoThisGroup": false,
            "bookmarkId": null,
            "showOnlyActiveTabAfterMovingItIntoThisGroup": false,
            "discardTabsAfterHide": false,
            "discardExcludeAudioTabs": false,
            "prependTitleToWindow": false,
            "exportToBookmarksWhenAutoBackup": true,
            "leaveBookmarksOfClosedTabs": false,
            "moveToGroupIfNoneCatchTabRules": null
        },
        {
            "id": 2,
            "title": "Dev",
            "iconColor": "#3c78d8",
            "iconUrl": null,
            "iconViewType": "squares",
            "tabs": [
                {
                    "url": "https://supabase.com/dashboard/project/oodkzdiqsrwwrsjxcjzo/editor/144150",
                    "title": "feedbacks | Carbyn | dev@carbyn.io's Org | Supabase",
                    "cookieStoreId": "firefox-container-7",
                    "id": 6
                },
                {
                    "url": "https://supabase.com/dashboard/project/oodkzdiqsrwwrsjxcjzo/auth/policies?search=29160",
                    "title": "Auth | Supabase",
                    "cookieStoreId": "firefox-container-7",
                    "id": 9
                },
                {
                    "url": "https://app.lemonsqueezy.com/products",
                    "title": "Lemon Squeezy",
                    "cookieStoreId": "firefox-container-7",
                    "id": 12
                },
                {
                    "url": "https://docs.lemonsqueezy.com/api/variants",
                    "title": "Variants: Lemon Squeezy",
                    "cookieStoreId": "firefox-container-7",
                    "id": 13
                },
                {
                    "url": "https://github.com/CarbynIO/Carbyn/commits/pre-prod",
                    "title": "Commits · CarbynIO/Carbyn",
                    "cookieStoreId": "firefox-container-7",
                    "id": 14
                }
            ],
            "isArchive": false,
            "newTabContainer": "firefox-container-7",
            "ifDifferentContainerReOpen": false,
            "excludeContainersForReOpen": [],
            "isSticky": false,
            "catchTabContainers": [
                "firefox-container-7"
            ],
            "catchTabRules": "",
            "muteTabsWhenGroupCloseAndRestoreWhenOpen": false,
            "showTabAfterMovingItIntoThisGroup": false,
            "bookmarkId": null,
            "showOnlyActiveTabAfterMovingItIntoThisGroup": false,
            "discardTabsAfterHide": false,
            "discardExcludeAudioTabs": false,
            "prependTitleToWindow": false,
            "exportToBookmarksWhenAutoBackup": true,
            "leaveBookmarksOfClosedTabs": false,
            "moveToGroupIfNoneCatchTabRules": null
        }
    ],
    "lastCreatedGroupPosition": 3,
    "defaultGroupProps": {
        "iconViewType": "squares",
        "exportToBookmarksWhenAutoBackup": true
    },
    "closePopupAfterChangeGroup": true,
    "closePopupAfterSelectTab": false,
    "openGroupAfterChange": false,
    "alwaysAskNewGroupName": true,
    "createNewGroupWhenOpenNewWindow": false,
    "openManageGroupsInTab": true,
    "showConfirmDialogBeforeGroupArchiving": true,
    "showConfirmDialogBeforeGroupDelete": true,
    "showNotificationAfterGroupDelete": true,
    "showContextMenuOnTabs": true,
    "showContextMenuOnLinks": true,
    "defaultBookmarksParent": "toolbar_____",
    "showExtendGroupsPopupWithActiveTabs": false,
    "showTabsWithThumbnailsInManageGroups": false,
    "fullPopupWidth": false,
    "temporaryContainerTitle": "⌚Temporary Container",
    "contextMenuTab": [
        "open-in-new-window",
        "reload",
        "discard",
        "remove",
        "update-thumbnail",
        "set-group-icon",
        "move-tab-to-group"
    ],
    "contextMenuGroup": [
        "open-in-new-window",
        "sort-asc",
        "sort-desc",
        "discard",
        "discard-other",
        "export-to-bookmarks",
        "unload",
        "archive",
        "rename",
        "reload-all-tabs"
    ],
    "autoBackupEnable": true,
    "autoBackupLastBackupTimeStamp": 1693811981,
    "autoBackupIntervalKey": "days",
    "autoBackupIntervalValue": 1,
    "autoBackupIncludeTabThumbnails": true,
    "autoBackupIncludeTabFavIcons": false,
    "autoBackupFolderName": "STG-backups-FF-112.0.1-2",
    "autoBackupByDayIndex": true,
    "theme": "dark",
    "hotkeys": [
        {
            "action": "load-custom-group",
            "groupId": 1,
            "value": "Ctrl+1"
        },
        {
            "action": "load-custom-group",
            "groupId": 3,
            "value": "Ctrl+2"
        },
        {
            "action": "load-custom-group",
            "groupId": 2,
            "value": "Ctrl+3"
        }
    ],
    "containers": {
        "firefox-container-1": {
            "name": "Personal",
            "icon": "chill",
            "iconUrl": "resource://usercontext-content/chill.svg",
            "color": "red",
            "colorCode": "#ff613d",
            "cookieStoreId": "firefox-container-1"
        },
        "firefox-container-6": {
            "name": "Infosec",
            "icon": "fingerprint",
            "iconUrl": "resource://usercontext-content/fingerprint.svg",
            "color": "purple",
            "colorCode": "#af51f5",
            "cookieStoreId": "firefox-container-6"
        },
        "firefox-container-7": {
            "name": "Dev",
            "icon": "circle",
            "iconUrl": "resource://usercontext-content/circle.svg",
            "color": "blue",
            "colorCode": "#37adff",
            "cookieStoreId": "firefox-container-7"
        }
    }
}